twocan/__init__.py
twocan/base.py
twocan/callbacks.py
twocan/optimize.py
twocan/plotting.py
twocan/utils.py
twocan/.ipynb_checkpoints/optimize-checkpoint.py
twocan/.ipynb_checkpoints/utils-checkpoint.py
twocan/__pycache__/__init__.cpython-313.pyc
twocan/__pycache__/__init__.cpython-39.pyc
twocan/__pycache__/base.cpython-313.pyc
twocan/__pycache__/base.cpython-39.pyc
twocan/__pycache__/callbacks.cpython-313.pyc
twocan/__pycache__/callbacks.cpython-39.pyc
twocan/__pycache__/format_zarr.cpython-313.pyc
twocan/__pycache__/format_zarr.cpython-39.pyc
twocan/__pycache__/optimization.cpython-39.pyc
twocan/__pycache__/plotting.cpython-39.pyc
twocan/__pycache__/utils.cpython-313.pyc
twocan/__pycache__/utils.cpython-39.pyc
twocan/__pycache__/workflow.cpython-39.pyc
twocan-0.1.2.dist-info/licenses/LICENSE
twocan-0.1.2.dist-info/METADATA
twocan-0.1.2.dist-info/WHEEL
twocan-0.1.2.dist-info/top_level.txt
twocan-0.1.2.dist-info/RECORD
