Metadata-Version: 2.4
Name: twocan
Version: 0.1.2
Summary: A Bayesian optimization framework for multimodal registration of highly multiplexed single-cell spatial proteomics data
Home-page: https://github.com/camlab-bioml/twocan
Author: Caitlin F. Harrigan
Author-email: caitlin.harrigan@mail.utoronto.ca
Project-URL: Documentation, https://twocan.readthedocs.io/
Project-URL: Source, https://github.com/camlab-bioml/twocan
Keywords: spatial-proteomics highly-multiplexed-imaging cross-modality-registration bayesian-optimization
Classifier: Development Status :: 4 - Beta
Classifier: Intended Audience :: Science/Research
Classifier: Operating System :: OS Independent
Classifier: Programming Language :: Python :: 3
Classifier: Programming Language :: Python :: 3.8
Classifier: Programming Language :: Python :: 3.9
Classifier: Programming Language :: Python :: 3.10
Classifier: Programming Language :: Python :: 3.11
Classifier: Topic :: Scientific/Engineering :: Bio-Informatics
Classifier: Topic :: Scientific/Engineering :: Image Processing
Requires-Python: >=3.8
License-File: LICENSE
Requires-Dist: numpy>=1.19.0
Requires-Dist: pandas>=1.3.0
Requires-Dist: opencv-python>=4.5.0
Requires-Dist: scikit-image>=0.18.0
Requires-Dist: scikit-learn>=1.0.0
Requires-Dist: spatialdata>=0.1.0
Requires-Dist: optuna>=3.0.0
Requires-Dist: tifffile>=2021.1.1
Requires-Dist: matplotlib>=3.3.0
Requires-Dist: scipy>=1.7.0
Provides-Extra: dev
Requires-Dist: pytest>=6.0; extra == "dev"
Requires-Dist: black>=22.0; extra == "dev"
Requires-Dist: flake8>=4.0; extra == "dev"
Requires-Dist: isort>=5.0; extra == "dev"
Requires-Dist: pre-commit>=2.0; extra == "dev"
Requires-Dist: jupyter>=1.0; extra == "dev"
Provides-Extra: docs
Requires-Dist: sphinx>=4.0; extra == "docs"
Requires-Dist: sphinx-rtd-theme; extra == "docs"
Requires-Dist: myst-parser; extra == "docs"
Requires-Dist: myst-nb; extra == "docs"
Requires-Dist: nbsphinx; extra == "docs"
Requires-Dist: sphinx-autobuild; extra == "docs"
Requires-Dist: sphinx-copybutton; extra == "docs"
Requires-Dist: sphinxcontrib-bibtex; extra == "docs"
Provides-Extra: notebooks
Requires-Dist: jupyter>=1.0; extra == "notebooks"
Requires-Dist: ipywidgets>=7.0; extra == "notebooks"
Dynamic: author
Dynamic: author-email
Dynamic: classifier
Dynamic: description
Dynamic: description-content-type
Dynamic: home-page
Dynamic: keywords
Dynamic: license-file
Dynamic: project-url
Dynamic: provides-extra
Dynamic: requires-dist
Dynamic: requires-python
Dynamic: summary
